configator/__init__.py
configator/consts.py
configator/envars.py
configator/engine/__init__.py
configator/engine/connector.py
configator/engine/container.py
configator/engine/observer.py
configator/engine/publisher.py
configator/engine/subscriber.py
configator/extensions/__init__.py
configator/extensions/logging.py
configator/extensions/sequence.py
configator/extensions/storage.py
configator/utils/__init__.py
configator/utils/datatype.py
configator/utils/datatype_util.py
configator/utils/datetime_util.py
configator/utils/exithook.py
configator/utils/function.py
configator/utils/function_util.py
configator/utils/logging.py
configator/utils/signal_util.py
configator/utils/signfunc.py
configator/utils/string_util.py
configator/utils/system_util.py
configator/utils/trackback_util.py
configator-0.1.10.dist-info/LICENSE.txt
configator-0.1.10.dist-info/METADATA
configator-0.1.10.dist-info/WHEEL
configator-0.1.10.dist-info/top_level.txt
configator-0.1.10.dist-info/RECORD
