Metadata-Version: 2.1
Name: configator
Version: 0.1.10
Summary: A simple CONFIGuration propagATOR
Home-page: https://github.com/skelethon/configator
Author: skelethon
License: GPL-3.0
Download-URL: https://github.com/skelethon/configator/downloads
Keywords: configuration,redis,pub/sub
Platform: UNKNOWN
Requires-Python: >=2.7,!=3.0.*,!=3.1.*,!=3.2.*,!=3.3.*
Requires-Dist: deepdiff
Requires-Dist: readerwriterlock
Requires-Dist: redis
